coordinator_data_tasks/__init__.py
coordinator_data_tasks/cli.py
coordinator_data_tasks/coordinator_data_tasks.py
coordinator_data_tasks-0.0.5.dist-info/DESCRIPTION.rst
coordinator_data_tasks-0.0.5.dist-info/METADATA
coordinator_data_tasks-0.0.5.dist-info/RECORD
coordinator_data_tasks-0.0.5.dist-info/WHEEL
coordinator_data_tasks-0.0.5.dist-info/entry_points.txt
coordinator_data_tasks-0.0.5.dist-info/metadata.json
coordinator_data_tasks-0.0.5.dist-info/top_level.txt
