Metadata-Version: 2.0
Name: coordinator-data-tasks
Version: 0.0.5
Summary: A python-based command line utility to automate some of the most common data tasks faced by the Clinical Coordinators.
Home-page: https://github.com/xguse/coordinator_data_tasks
Author: Gus Dunn
Author-email: w.gus.dunn@gmail.com
License: MIT license
Keywords: coordinator_data_tasks
Platform: UNKNOWN
Classifier: Development Status :: 2 - Pre-Alpha
Classifier: Intended Audience :: Developers
Classifier: License :: OSI Approved :: MIT License
Classifier: Natural Language :: English
Classifier: Programming Language :: Python :: 3.5
Classifier: Programming Language :: Python :: 3.6
Requires-Dist: click
Requires-Dist: pandas
Requires-Dist: jupyter
Requires-Dist: jupyter-nbextensions-configurator
Requires-Dist: numpy
Requires-Dist: recommonmark
Requires-Dist: logzero
Requires-Dist: tqdm (>=4.10.0)
Requires-Dist: jupyter-contrib-nbextensions
Requires-Dist: seaborn
Requires-Dist: numexpr
Requires-Dist: xlrd
Requires-Dist: munch
Requires-Dist: widgetsnbextension
Requires-Dist: xlwt
Requires-Dist: ipython
